harlequin_datafusion/__init__.py
harlequin_datafusion/adapter.py
harlequin_datafusion/py.typed
harlequin_datafusion-0.1.2.dist-info/LICENSE
harlequin_datafusion-0.1.2.dist-info/METADATA
harlequin_datafusion-0.1.2.dist-info/WHEEL
harlequin_datafusion-0.1.2.dist-info/entry_points.txt
harlequin_datafusion-0.1.2.dist-info/RECORD
